LICENSE
LICENSE.txt
README.rst
setup.cfg
setup.py
Godream/__init__.py
Godream/classification.py
Godream/convertool.py
Godream/geobox.py
Godream/indices.py
Godream/model.py
Godream/plotimg.py
Godream.egg-info/PKG-INFO
Godream.egg-info/SOURCES.txt
Godream.egg-info/dependency_links.txt
Godream.egg-info/requires.txt
Godream.egg-info/top_level.txt