Metadata-Version: 2.1
Name: Godream
Version: 0.1.2
Summary: This is a library that contain geospatial tools in python for Remote sensing and GIS applications. This project is part of Open data of Gistda project. 
Home-page: https://github.com/DreamPTK/Godream
Download-URL: https://github.com/DreamPTK/Godream/archive/refs/tags/v0.0.1.zip
Author: Pathakorn Usaha
Author-email: dreamusaha@gmail.com
License: MIT
Keywords: geography,geospatial,GIS,RS,Geospatial analysis
Classifier: Development Status :: 3 - Alpha
Classifier: Intended Audience :: Science/Research
Classifier: Topic :: Software Development :: Build Tools
Classifier: License :: OSI Approved :: MIT License
Classifier: Programming Language :: Python :: 3.9
License-File: LICENSE
License-File: LICENSE.txt
Requires-Dist: dask
Requires-Dist: dask_ml
Requires-Dist: xarray
Requires-Dist: joblib
Requires-Dist: datacube
Requires-Dist: rasterio
Requires-Dist: rioxarray
Requires-Dist: geopandas
Requires-Dist: jsons
Requires-Dist: numpy
Requires-Dist: matplotlib
Requires-Dist: scikit-learn
Requires-Dist: folium
Requires-Dist: flusstools
Requires-Dist: shapely
